Metadata-Version: 1.2
Name: mediawikiTool
Version: 0.6.0
Summary: A command line tool for mediawiki file format covert and so on.
Home-page: https://github.com/snakeclub/mediawikiTool
Author: 黎慧剑
Author-email: snakeclub@163.com
Maintainer: 黎慧剑
Maintainer-email: snakeclub@163.com
License: Mozilla Public License 2.0
Keywords: MediaWiki Tool
Platform: all
Classifier: Operating System :: OS Independent
Classifier: License :: OSI Approved :: Mozilla Public License 2.0 (MPL 2.0)
Classifier: Programming Language :: Python :: 3.6
Classifier: Topic :: Software Development :: Libraries
